bson/__init__.py
bson/codec.py
bson/network.py
bson/objectid.py
bson/py3compat.py
bson/types.py
bson/tz_util.py
bson_senao-0.5.10.dist-info/METADATA
bson_senao-0.5.10.dist-info/WHEEL
bson_senao-0.5.10.dist-info/licenses/LICENSE
bson_senao-0.5.10.dist-info/licenses/LICENSE_APACHE
bson_senao-0.5.10.dist-info/RECORD
