Metadata-Version: 2.4
Name: bson_senao
Version: 0.5.10
Summary: BSON codec for Python
Project-URL: Homepage, https://github.com/sheiun-xu/bson
Author-email: Ayun Park <iamparkayun@gmail.com>, Sheiun Xu <sheiun103254@gmail.com>
License-Expression: BSD-3-Clause
License-File: LICENSE
License-File: LICENSE_APACHE
Keywords: BSON,codec
Classifier: Programming Language :: Python :: 3
Classifier: Programming Language :: Python :: 3.9
Classifier: Programming Language :: Python :: 3.10
Classifier: Programming Language :: Python :: 3.11
Classifier: Programming Language :: Python :: 3.12
Classifier: Programming Language :: Python :: 3.13
Classifier: Programming Language :: Python :: 3.14
Requires-Python: >=3.9
Requires-Dist: python-dateutil>=2.4.0
Requires-Dist: six>=1.9.0
